npd_wraper/__init__.py
npd_wraper/npd_baa.py
npd_wraper/npd_company.py
npd_wraper/npd_discovery.py
npd_wraper/npd_facility.py
npd_wraper/npd_fields.py
npd_wraper/npd_shape.py
npd_wraper/npd_stratigraphy.py
npd_wraper/npd_wells.py
npd_wraper/npd_wraper.py
npd_data-0.1.4.dist-info/LICENSE
npd_data-0.1.4.dist-info/METADATA
npd_data-0.1.4.dist-info/WHEEL
npd_data-0.1.4.dist-info/top_level.txt
npd_data-0.1.4.dist-info/RECORD
