Metadata-Version: 2.1
Name: npd-data
Version: 0.1.4
Summary: Wraper NCS data from NPD
Home-page: UNKNOWN
Author: Merouane Hamdani
Author-email: merouaneh@yahoo.fr
License: UNKNOWN
Platform: UNKNOWN
Classifier: Programming Language :: Python :: 3
Classifier: License :: OSI Approved :: MIT License
Classifier: Operating System :: OS Independent
Classifier: Topic :: Software Development
Requires-Python: >=3.6
Requires-Dist: numpy
Requires-Dist: pandas
Requires-Dist: requests
Requires-Dist: geopandas
